genlink/__init__.py
genlink/__version__.py
genlink/agent.py
genlink/logger.py
genlink/typedicts.py
genlink/utils.py
genlink/connector/__init__.py
genlink/connector/anthropic.py
genlink/connector/baseconnector.py
genlink/connector/gemini.py
genlink/connector/openai.py
genlink-0.1.2a0.dist-info/LICENSE
genlink-0.1.2a0.dist-info/METADATA
genlink-0.1.2a0.dist-info/WHEEL
genlink-0.1.2a0.dist-info/top_level.txt
genlink-0.1.2a0.dist-info/RECORD
