Metadata-Version: 2.1
Name: genlink
Version: 0.1.2a0
Summary: Common interface for llm apis
License: MIT
Project-URL: repository, https://gitlab.com/lahloumimiahmed11/genlink
Requires-Python: >=3.10
License-File: LICENSE
Requires-Dist: openai~=1.57.0
Requires-Dist: google-generativeai~=0.7.2
Requires-Dist: anthropic~=0.40.0
Requires-Dist: PyYAML
Requires-Dist: types-PyYAML
Requires-Dist: pydantic
Requires-Dist: typing-extensions~=4.12.0
Provides-Extra: dev
Requires-Dist: ruff; extra == "dev"
Requires-Dist: mypy; extra == "dev"
Requires-Dist: pytest; extra == "dev"
Requires-Dist: pytest-asyncio; extra == "dev"
